scProportionTest/__init__.py
scProportionTest/_cluster_map.py
scProportionTest/_multiple_permutation_dot_plot.py
scProportionTest/_multiple_permutation_test.py
scProportionTest/_multiple_point_range_plot.py
scProportionTest/_permutation_test.py
scProportionTest/_point_range_plot.py
py_scProportionTest-0.1.2.dist-info/METADATA
py_scProportionTest-0.1.2.dist-info/WHEEL
py_scProportionTest-0.1.2.dist-info/top_level.txt
py_scProportionTest-0.1.2.dist-info/RECORD
