Metadata-Version: 2.1
Name: py-scProportionTest
Version: 0.1.2
Summary: Python package to evaluate differences in cell type proportions
Home-page: https://github.com/SamuelAMiller1/py-scProportionTest
Author: Sam Miller
Requires-Dist: numpy
Requires-Dist: pandas
Requires-Dist: statsmodels
Requires-Dist: matplotlib
Requires-Dist: tqdm
Requires-Dist: seaborn
